timey_wimey/__init__.py
timey_wimey/main.py
timey_wimey-0.1.2.dist-info/METADATA
timey_wimey-0.1.2.dist-info/WHEEL
timey_wimey-0.1.2.dist-info/entry_points.txt
timey_wimey-0.1.2.dist-info/RECORD
