Metadata-Version: 2.1
Name: timey-wimey
Version: 0.1.2
Summary: A simple CLI for generating times
License: MIT
Author: Sam Phinizy
Author-email: 83414895+sam-phinizy@users.noreply.github.com
Requires-Python: >=3.11,<4.0
Classifier: License :: OSI Approved :: MIT License
Classifier: Programming Language :: Python :: 3
Classifier: Programming Language :: Python :: 3.11
Requires-Dist: dateparser (>=1.1.8,<2.0.0)
Requires-Dist: pendulum (>=2.1.2,<3.0.0)
Requires-Dist: sentinel (>=1.0.0,<2.0.0)
Requires-Dist: typer (>=0.9.0,<0.10.0)
Requires-Dist: tzlocal (>=5.0.1,<6.0.0)
